[{"isVirtual":false,"filePath":"projects/Worm Update(1)/BP/functions/worm/burrow.mcfunction","aliases":[],"requiredFiles":["projects/Worm Update(1)/BP/commands/**/*.[jt]s","projects/Worm Update(1)/BP/commands/*.[jt]s"],"updateFiles":[]},{"isVirtual":false,"filePath":"projects/Worm Update(1)/BP/functions/worm/timer.mcfunction","aliases":[],"requiredFiles":["projects/Worm Update(1)/BP/commands/**/*.[jt]s","projects/Worm Update(1)/BP/commands/*.[jt]s"],"updateFiles":[]},{"isVirtual":false,"filePath":"projects/Worm Update(1)/BP/functions/worm/worm.mcfunction","aliases":[],"requiredFiles":["projects/Worm Update(1)/BP/commands/**/*.[jt]s","projects/Worm Update(1)/BP/commands/*.[jt]s"],"updateFiles":[]},{"isVirtual":false,"filePath":"projects/Worm Update(1)/BP/functions/tick.json","aliases":[],"requiredFiles":[],"updateFiles":[]}]